{"name":"Cardápio RU","tagline":"Aplicativo do Cardápio do Restaurante Universitário da UFRN para Windows Phone","body":"Bem vindo à página oficiosa do app não oficioso do Restaurante Universitário da UFRN para Windows Phone. \r\n\r\nAqui você vai achar todas as informações necessárias para ajudar no desenvolvimento desse projeto tão divertido.\r\n\r\nAtualmente, com o CRU, você pode:\r\n* Ver pratos offline\r\n* Consultar horários\r\n\r\nEstamos vendo a possibilidade de adicionar as seguintes funcionalidades:\r\n* Alerta quando houver os pratos selecionados\r\n* Mapa com os locais de interesse (carregar cartão, por exemplo)\r\n\r\nTem mais sugestões? \r\nNos conte [aqui](https://github.com/BlackBerets/Cardapio/issues/new) ou mande um e-mail para [Thiago Jedi](mailto:thiagojedi@live.it)\r\n\r\n\r\nVersão 1.0.1.0\r\n----\r\n- Corrigido bug do Desjejum\r\n- Corrigido bug do apóstofo, como em \"Farofa D'água\" que aparecia \"Farofa D&acute;agua\"","google":"","note":"Don't delete this file! It's used internally to help with page regeneration."}